bio2bel_drugbank/__init__.py
bio2bel_drugbank/__main__.py
bio2bel_drugbank/cli.py
bio2bel_drugbank/constants.py
bio2bel_drugbank/manager.py
bio2bel_drugbank/models.py
bio2bel_drugbank/parser.py
bio2bel_drugbank/patent_utils.py
bio2bel_drugbank/utils.py
bio2bel_drugbank/web.py
bio2bel_drugbank-0.1.1.dist-info/LICENSE
bio2bel_drugbank-0.1.1.dist-info/METADATA
bio2bel_drugbank-0.1.1.dist-info/WHEEL
bio2bel_drugbank-0.1.1.dist-info/entry_points.txt
bio2bel_drugbank-0.1.1.dist-info/top_level.txt
bio2bel_drugbank-0.1.1.dist-info/RECORD
